analysta_index/__init__.py
analysta_index/indexer.py
analysta_index/document_loaders/AnalystaBDDScenariosLoader.py
analysta_index/document_loaders/AnalystaCSVLoader.py
analysta_index/document_loaders/AnalystaConfluenceLoader.py
analysta_index/document_loaders/AnalystaDirectoryLoader.py
analysta_index/document_loaders/AnalystaExcelLoader.py
analysta_index/document_loaders/AnalystaGitRepoLoader.py
analysta_index/document_loaders/AnalystaQtestLoader.py
analysta_index/document_loaders/AnalystaTableLoader.py
analysta_index/document_loaders/__init__.py
analysta_index/document_loaders/constants.py
analysta_index/document_loaders/utils.py
analysta_index/interfaces/__init__.py
analysta_index/interfaces/kwextractor.py
analysta_index/interfaces/llm_processor.py
analysta_index/interfaces/loaders.py
analysta_index/interfaces/splitters.py
analysta_index/llms/__init__.py
analysta_index/llms/analysta.py
analysta_index/llms/preloaded.py
analysta_index/retrievers/AnalystaRetriever.py
analysta_index/retrievers/SimpleRetriever.py
analysta_index/retrievers/VectorstoreRetriever.py
analysta_index/retrievers/__init__.py
analysta_index/tools/__init__.py
analysta_index/tools/git.py
analysta_index/tools/log.py
analysta_index/tools/quota.py
analysta_index/tools/state.py
analysta_index/tools/utils.py
analysta_index/tools/vector.py
analysta_index/tools/bdd_parser/__init__.py
analysta_index/tools/bdd_parser/bdd_exceptions.py
analysta_index/tools/bdd_parser/bdd_parser.py
analysta_index/tools/bdd_parser/feature_types.py
analysta_index/tools/bdd_parser/parser.py
analysta_index-0.2.72.dist-info/LICENSE
analysta_index-0.2.72.dist-info/METADATA
analysta_index-0.2.72.dist-info/WHEEL
analysta_index-0.2.72.dist-info/top_level.txt
analysta_index-0.2.72.dist-info/RECORD
