Metadata-Version: 2.1
Name: analysta_index
Version: 0.2.72
Summary: Extension of Langchain loaders, llms and retrievers for Analysta
Author-email: Artem Rozumenko <support@analysta.ai>
Project-URL: Homepage, https://analysta.ai
Project-URL: Issues, https://github.com/analysta-ai/indexer/issues
Classifier: Programming Language :: Python :: 3
Classifier: License :: OSI Approved :: Apache Software License
Classifier: Operating System :: OS Independent
Requires-Python: >=3.7
License-File: LICENSE
Requires-Dist: langchain ~=0.2.0
Requires-Dist: langchain-chroma ~=0.1.0
Requires-Dist: langchain-unstructured ~=0.1.2
Requires-Dist: keybert ==0.8.3
Requires-Dist: charset-normalizer ==3.3.2
Requires-Dist: unstructured[local-inference] ==0.15.9
Requires-Dist: unstructured-pytesseract ==0.3.13
Requires-Dist: unstructured-inference ==0.7.36
Requires-Dist: python-pptx ==1.0.2
Requires-Dist: pdf2image ==1.16.3
Requires-Dist: pikepdf ==8.7.1
Requires-Dist: pypdf ==4.3.1
Requires-Dist: pdfminer.six ==20221105
Requires-Dist: opencv-python ==4.8.1.78
Requires-Dist: pandas ==2.1.3
Requires-Dist: python-docx ==1.1.2
Requires-Dist: openpyxl ==3.1.2
Requires-Dist: markdown ==3.5.1
Requires-Dist: beautifulsoup4 ==4.12.2
Requires-Dist: gensim ==4.3.2
Requires-Dist: chromadb ==0.4.1
Requires-Dist: pgvector ==0.2.5
Requires-Dist: openai >=1.24.0
Requires-Dist: tiktoken >=0.7.0
Requires-Dist: atlassian-python-api ~=3.41
Requires-Dist: markdownify ==0.12.1
Requires-Dist: python-dotenv ~=1.0.1
Requires-Dist: dulwich ==0.21.6
Requires-Dist: paramiko ==3.3.1
Requires-Dist: urllib3 >=2
Requires-Dist: requests ~=2.3
Requires-Dist: certifi ==2024.8.30
Requires-Dist: scipy ==1.10.1
Requires-Dist: qtest-swagger-client ==0.0.3
Requires-Dist: pytesseract ==0.3.13
Requires-Dist: pillow ==10.3.0
Requires-Dist: reportlab ==4.2.5
Requires-Dist: svglib ==1.5.1
Requires-Dist: rlpycairo ==0.3.0
Requires-Dist: cairocffi ==1.7.1
Requires-Dist: docx2txt ==0.8
